Metadata-Version: 2.1
Name: scratchlib
Version: 0.10.0
Summary: wrapper for api scratch
Author: Noverdo-Gagarinten[CodTen]
Author-email: dasfasru@gmail.com
